plone.testing-6.1.0-py2.7-nspkg.pth
plone/testing/README.rst
plone/testing/__init__.py
plone/testing/_z2_testbrowser.py
plone/testing/layer.py
plone/testing/layer.rst
plone/testing/publisher.py
plone/testing/publisher.rst
plone/testing/security.py
plone/testing/security.rst
plone/testing/testing_zca.zcml
plone/testing/testing_zca_more_specific.zcml
plone/testing/tests.py
plone/testing/z2.py
plone/testing/z2.rst
plone/testing/zca.py
plone/testing/zca.rst
plone/testing/zodb.py
plone/testing/zodb.rst
plone.testing-6.1.0.dist-info/METADATA
plone.testing-6.1.0.dist-info/RECORD
plone.testing-6.1.0.dist-info/WHEEL
plone.testing-6.1.0.dist-info/namespace_packages.txt
plone.testing-6.1.0.dist-info/top_level.txt
