Metadata-Version: 2.1
Name: plone.testing
Version: 6.1.0
Summary: Testing infrastructure for Zope and Plone projects.
Home-page: https://github.com/plone/plone.testing
Author: Plone Foundation
Author-email: plone-developers@lists.sourceforge.net
License: BSD
Keywords: plone zope testing
Platform: UNKNOWN
Classifier: Environment :: Web Environment
Classifier: Framework :: Plone
Classifier: Framework :: Plone :: 5.2
Classifier: Operating System :: OS Independent
Classifier: Programming Language :: Python
Classifier: Programming Language :: Python :: 2.7
Classifier: Topic :: Internet :: WWW/HTTP :: Dynamic Content
Classifier: License :: OSI Approved :: BSD License
Provides-Extra: publisher
Provides-Extra: zca
Provides-Extra: zodb
Provides-Extra: test
Provides-Extra: security
Provides-Extra: z2
Requires-Dist: setuptools
Requires-Dist: zope.testing
Provides-Extra: publisher
Requires-Dist: zope.configuration; extra == 'publisher'
Requires-Dist: zope.security; extra == 'publisher'
Requires-Dist: zope.browsermenu; extra == 'publisher'
Requires-Dist: zope.browserpage; extra == 'publisher'
Requires-Dist: zope.browserresource; extra == 'publisher'
Requires-Dist: zope.publisher; extra == 'publisher'
Provides-Extra: security
Requires-Dist: zope.security; extra == 'security'
Provides-Extra: test
Requires-Dist: ZODB3; extra == 'test'
Requires-Dist: zope.browsermenu; extra == 'test'
Requires-Dist: zope.browserpage; extra == 'test'
Requires-Dist: zope.browserresource; extra == 'test'
Requires-Dist: zope.component; extra == 'test'
Requires-Dist: zope.configuration; extra == 'test'
Requires-Dist: zope.event; extra == 'test'
Requires-Dist: zope.interface; extra == 'test'
Requires-Dist: zope.publisher; extra == 'test'
Requires-Dist: zope.security; extra == 'test'
Requires-Dist: zope.testbrowser; extra == 'test'
Requires-Dist: zope.testrunner; extra == 'test'
Requires-Dist: Zope; extra == 'test'
Requires-Dist: ZServer; extra == 'test'
Provides-Extra: z2
Requires-Dist: Zope; extra == 'z2'
Requires-Dist: zope.component; extra == 'z2'
Requires-Dist: zope.testbrowser; extra == 'z2'
Requires-Dist: zope.publisher; extra == 'z2'
Provides-Extra: zca
Requires-Dist: zope.component; extra == 'zca'
Requires-Dist: zope.event; extra == 'zca'
Requires-Dist: zope.configuration; extra == 'zca'
Provides-Extra: zodb
Requires-Dist: ZODB3; extra == 'zodb'
